pipes/__init__.py
pipes/__main__.py
pipes/config.py
pipes/pipes.py
pipes/renderer.py
pipes/types.py
pipes_py-2.0.0.dist-info/METADATA
pipes_py-2.0.0.dist-info/WHEEL
pipes_py-2.0.0.dist-info/entry_points.txt
pipes_py-2.0.0.dist-info/licenses/LICENSE
pipes_py-2.0.0.dist-info/RECORD
